penut/__init__.py
penut/io.py
penut/utils.py
penut-0.0.2.dist-info/LICENSE
penut-0.0.2.dist-info/METADATA
penut-0.0.2.dist-info/WHEEL
penut-0.0.2.dist-info/top_level.txt
penut-0.0.2.dist-info/RECORD
