Metadata-Version: 2.1
Name: penut
Version: 0.0.2
Summary: This is a collection of my useful functions.
Home-page: https://github.com/penut85420/Penut
Author: PenutChen
Author-email: penut85420@gmail.com
License: UNKNOWN
Platform: UNKNOWN
Classifier: Programming Language :: Python :: 3
Classifier: License :: OSI Approved :: MIT License
Classifier: Operating System :: OS Independent
Requires-Python: >=3.6
